ua_gen/__init__.py
ua_gen/cli.py
ua_gen/consts.py
ua_gen/db_manager.py
ua_gen/exceptions.py
ua_gen/logging.py
ua_gen/ua_rules.py
useragent_picker_cli-0.1.4.dist-info/METADATA
useragent_picker_cli-0.1.4.dist-info/WHEEL
useragent_picker_cli-0.1.4.dist-info/entry_points.txt
useragent_picker_cli-0.1.4.dist-info/top_level.txt
useragent_picker_cli-0.1.4.dist-info/RECORD
