Metadata-Version: 2.1
Name: useragent-picker-cli
Version: 0.1.4
Summary: Generates random but realistic user agents on a command line (or via API)
Home-page: https://github.com/chorsley/useragent-picker-cli
Author: Chris Horsley
Author-email: cmrhorsley@gmail.com
License: BSD
Platform: any
Classifier: Development Status :: 4 - Beta
Classifier: Environment :: Console
Classifier: Intended Audience :: Developers
Classifier: License :: OSI Approved :: BSD License
Classifier: Operating System :: POSIX
Classifier: Operating System :: MacOS
Classifier: Operating System :: Unix
Classifier: Operating System :: Microsoft :: Windows
Classifier: Programming Language :: Python
Classifier: Programming Language :: Python :: 3
Classifier: Topic :: Software Development :: Libraries :: Python Modules
Requires-Dist: certifi (==2020.6.20)
Requires-Dist: chardet (==3.0.4)
Requires-Dist: docopt (==0.6.2)
Requires-Dist: loguru (==0.5.1)
Requires-Dist: requests (==2.24.0)
Requires-Dist: ua-parser (==0.10.0)
Requires-Dist: user-agents (==2.1)
Requires-Dist: aiocontextvars (==0.2.2) ; python_version < "3.7"
Requires-Dist: contextvars (==2.4) ; python_version < "3.7"
Requires-Dist: idna (==2.10) ; python_version >= "2.7" and python_version not in "3.0, 3.1, 3.2, 3.3"
Requires-Dist: urllib3 (==1.25.9) ; python_version >= "2.7" and python_version not in "3.0, 3.1, 3.2, 3.3, 3.4" and python_version < "4"
Requires-Dist: immutables (==0.14) ; python_version >= "3.5"
